<?xml version="1.0" encoding="UTF-8" standalone="yes"?>

	<channel>
	<items>
    
		<item>
		<title>[COLOR deepskyblue][B]•[/B][/COLOR][COLOR red][B]TV[/B][/COLOR]</title>
		<link>http://ignorame</link>
		<externallink>https://raw.githubusercontent.com/thanh51/repository.thanh51/master/TV.xml</externallink>
		</item>

		 <item>
		<title>[COLOR deepskyblue][B]•[/B][/COLOR][COLOR red][B]PHIM[/B][/COLOR]</title>
		<link>http://ignorame</link>
		<externallink>https://raw.githubusercontent.com/thanh51/repository.thanh51/master/Phim.xml</externallink>
		</item>

		 <item>
		<title>[COLOR deepskyblue][B]•[/B][/COLOR][COLOR red][B]CA NHAC[/B][/COLOR]</title>
		<link>http://ignorame</link>
		<externallink>https://raw.githubusercontent.com/thanh51/repository.thanh51/master/CaNhac.m3u</externallink>
		</item>

		 <item>
		<title>[COLOR deepskyblue][B]•[/B][/COLOR][COLOR red][B]NHẠC & PHIM TRÊN YOUTUBE[/B][/COLOR]</title>
		<link>http://ignorame</link>
		<externallink>https://raw.githubusercontent.com/thanh51/repository.thanh51/master/NhacPhimYoutube.xml</externallink>
		</item>

		 <item>
		<title>[COLOR deepskyblue][B]•[/B][/COLOR][COLOR red][B]VIDEOS YOUTUBE TH[/B][/COLOR]</title>
		<link>http://ignorame</link>
		<externallink>https://raw.githubusercontent.com/thanh51/repository.thanh51/master/VideoYoutube.xml</externallink>
		</item>

		 <item>
		<title>[COLOR deepskyblue][B]•[/B][/COLOR][COLOR red][B]RADIO TH[/B][/COLOR]</title>
		<link>http://ignorame</link>
		<externallink>https://raw.githubusercontent.com/thanh51/repository.thanh51/master/RadioTH.m3u</externallink>
		</item>

	</items>
	</channel>
